{
   "elements":[
      {
         "id":"investigator1",
         "label":"Ispettore Wakefield",
         "aspects":{
            "hunter":1,
            "mortal":1,
            "meticulous":1,
            "grim":1
         },
         "description":"Zachary Wakefield: un melanconico ispettore di polizia senza alcun rimorso. È stato assegnato di recente al Dipartimento Soppressione.",
         "unique":true,
         "xtriggers":{
            "killmortal":"corpse",
            "killhunter":"corpse",
            "derangemortal":"zachary_r_c",
            "capturehunter":"investigator1prisoner",
            "dissolution":"influencewintere"
         }
      },
      {
         "id":"investigator2",
         "label":"Spencer Hobson",
         "aspects":{
            "hunter":1,
            "mortal":1,
            "mystic":1,
            "erratic":1
         },
         "description":"Hobson è stato giornalista, detective privato e, per un breve periodo, prete. Ora è un agente del Dipartimento Soppressione.",
         "unique":true,
         "xtriggers":{
            "killmortal":"corpse",
            "killhunter":"corpse",
            "derangemortal":"spencer_r_c",
            "capturehunter":"investigator2prisoner",
            "dissolution":"influenceknocke"
         }
      },
      {
         "id":"investigator3",
         "label":"Connie Lee",
         "aspects":{
            "hunter":1,
            "mortal":1,
            "tenacious":1,
            "mystic":1
         },
         "description":"Ereditiera, suffragetta ed avventuriera. Recentemente ha posto il suo donchisciottesco entusiasmo, nonché la sua considerabile ricchezza, al servizio del Dipartimento Soppressione.",
         "unique":true,
         "xtriggers":{
            "killmortal":"corpse",
            "killhunter":"corpse",
            "derangemortal":"connie_r_c",
            "capturehunter":"investigator3prisoner",
            "dissolution":"influenceedgee"
         }
      },
      {
         "id":"investigator4",
         "label":"Dottoressa Natalia Dragon",
         "aspects":{
            "hunter":1,
            "mortal":1,
            "idealist":1,
            "meticulous":1
         },
         "description":"È stata derisa nel mondo accademico per le sue analisi sulle storie alternative, ma l'irrisione l’ha solo resa più risoluta. Ora lavora con il Dipartimento Soppressione.",
         "unique":true,
         "xtriggers":{
            "killmortal":"corpse",
            "killhunter":"corpse",
            "derangemortal":"natalia_r_c",
            "capturehunter":"investigator4prisoner",
            "dissolution":"influencelanterne"
         }
      },
      {
         "id":"defaulthunter",
         "label":"Detective Sfinito",
         "aspects":{
            "hunter":1,
            "mortal":1
         },
         "description":"Questo gentiluomo preferirebbe di gran lunga esser lasciato in pace con la sua pipa e il suo London News Illustrato, ma no <i>apparentemente</i> qualche prestigiatore di abomini deve esser cacciato come un cane impazzito e <i>apparentemente</i> nessun altro poteva trovare del tempo.",
         "xtriggers":{
            "killmortal":"corpse",
            "killhunter":"corpse",
            "derangemortal":"douglas_r",
            "capturehunter":"defaulthunterprisoner",
            "dissolution":"influenceforgec"
         }
      },
      {
         "id":"investigator1prisoner",
         "label":"Ispettore Wakefield: Catturato!",
         "aspects":{
            "mortal":1,
            "prisoner":1,
            "lantern":3,
            "grail":3,
            "heart":3,
            "winter":4
         },
         "description":"Zachary Wakefield: un melanconico ispettore di polizia senza alcun rimorso. Assicuriamoci che muoia in cattività.",
         "unique":true,
         "xtriggers":{
            "killmortal":"corpse",
            "derangemortal":"zachary_r_c",
            "dissolution":"influencewintere"
         },
         "lifetime":600,
         "decayTo":"corpse"
      },
      {
         "id":"investigator2prisoner",
         "label":"Spencer Hobson: Catturato!",
         "aspects":{
            "prisoner":1,
            "mortal":1,
            "lantern":3,
            "grail":3,
            "heart":3,
            "knock":3
         },
         "description":"Hobson è stato giornalista, detective privato e, per un breve periodo, prete. Assicuriamoci che muoia in cattività.",
         "unique":true,
         "xtriggers":{
            "killmortal":"corpse",
            "derangemortal":"spencer_r_c",
            "dissolution":"influenceknocke"
         },
         "lifetime":600,
         "decayTo":"corpse"
      },
      {
         "id":"investigator3prisoner",
         "label":"Connie Lee: Catturata!",
         "aspects":{
            "prisoner":1,
            "mortal":1,
            "lantern":3,
            "grail":3,
            "heart":3,
            "edge":3
         },
         "description":"Ereditiera, suffragetta ed avventuriera. Assicuriamoci che muoia in cattività.",
         "unique":true,
         "xtriggers":{
            "killmortal":"corpse",
            "derangemortal":"connie_r_c",
            "dissolution":"influenceedgee"
         },
         "lifetime":600,
         "decayTo":"corpse"
      },
      {
         "id":"investigator4prisoner",
         "label":"Dottoressa Natalia Dragon: Catturata!",
         "aspects":{
            "prisoner":1,
            "mortal":1,
            "lantern":5,
            "grail":3,
            "heart":3
         },
         "description":"È stata derisa nel mondo accademico per le sue analisi sulle storie alternative, ma l'irrisione l’ha solo resa più risoluta.  Assicuriamoci che muoia in cattività.",
         "unique":true,
         "xtriggers":{
            "killmortal":"corpse",
            "derangemortal":"natalia_r_c",
            "dissolution":"influencelanterne"
         },
         "lifetime":600,
         "decayTo":"corpse"
      },
      {
         "id":"defaulthunterprisoner",
         "label":"Detective Sfinito: Catturato!",
         "aspects":{
            "mortal":1,
            "prisoner":1,
            "lantern":5,
            "grail":3,
            "heart":3
         },
         "description":"Questo gentiluomo preferirebbe di gran lunga esser lasciato in pace con la sua pipa e il suo London News Illustrato, ma ora è chiuso in qualche miserabile buco nella terra.",
         "xtriggers":{
            "killmortal":"corpse",
            "derangemortal":"douglas_r",
            "capturehunter":"defaulthunterprisoner",
            "dissolution":"influenceforgec"
         },
         "lifetime":600,
         "decayTo":"corpse"
      }
   ]
}