{
    "decks": [
        {
            "id": "locationscapital",
            "label": "Locais Ocultos na Capital",
            "description": "Lugares próximos.",
            "spec": [
                "vaultcapital1",
                "vaultcapital2",
                "vaultcapital3",
                "vaultcapital4",
                "vaultcapital5"
            ],
            "defaultcard": "vaultcapitaldefault",
            "resetonexhaustion": false
        },
        {
            "id": "vaultsshires",
            "label": "Locais Ocultos nos Condados",
            "description": "Quem sabe uma oportunidade para um dia no campo.",
            "spec": [
                "vaultshires1",
                "vaultshires2",
                "vaultshires3",
                "vaultshires4",
                "vaultshires5"
            ],
            "defaultcard": "vaultshiresdefault",
            "resetonexhaustion": false
        },
        {
            "id": "vaultscontinent",
            "label": "Locais Ocultos no Continente",
            "description": "Um mundo mais amplo encontra-se através do mar estreito.",
            "spec": [
                "vaultcontinent1",
                "vaultcontinent2",
                "vaultcontinent3",
                "vaultcontinent4",
                "vaultcontinent5",
                "vaultcontinent6"
            ],
            "defaultcard": "vaultcontinentdefault",
            "resetonexhaustion": false
        },
        {
            "id": "vaultslandbeyondforest",
            "label": "Locais Ocultos na Terra Além da Floresta",
            "description": "Uma pletora de possibilidades em uma terra montanhosa assombrada.",
            "spec": [
                "vaultlandbeyondforest1",
                "vaultlandbeyondforest2",
                "vaultlandbeyondforest3",
                "vaultlandbeyondforest4",
                "vaultlandbeyondforest5"
            ],
            "defaultcard": "vaultlandbeyondforestdefault",
            "resetonexhaustion": false
        },
        {
            "id": "vaultsrendingmountains",
            "label": "Locais Ocultos nas Cordilheiras do Suplício",
            "description": "Abóbadas e templos remotos e perigosos.",
            "spec": [
                "vaultrendingmountains1",
                "vaultrendingmountains2",
                "vaultrendingmountains3",
                "vaultrendingmountains4"
            ],
            "defaultcard": "vaultrendingmountainsdefault",
            "resetonexhaustion": false
        },
        {
            "id": "vaultsloneandlevelsands",
            "label": "Locais Ocultos nas Planícies Ermáticas",
            "description": "Aqui estão os tesouros da antiguidade, para aqueles que podem pegá-los.",
            "spec": [
                "vaultloneandlevelsands1",
                "vaultloneandlevelsands2",
                "vaultloneandlevelsands3",
                "vaultloneandlevelsands4"
            ],
            "defaultcard": "vaultloneandlevelsandsdefault",
            "resetonexhaustion": false
        },
        {
            "id": "vaultseveningisles",
            "label": "Locais Ocultos nas Ilhas Vespertinas",
            "description": "Ilhas não mapeadas ao redor do Porto Zênite.",
            "spec": [
                "vaulteveningisles1",
                "vaulteveningisles2",
                "vaulteveningisles3",
                "vaulteveningisles4"
            ],
            "defaultcard": "vaulteveningislesdefault",
            "resetonexhaustion": false
        }
    ]
}
